<Templates>
  <ToolOneVersion>5</ToolOneVersion>
  <Group>
    <Name>Items</Name>
    <Template>
      <Name>ActionItem</Name>
      <Properties>
        <GameAction>
          <ActorType>Handle</ActorType>
        </GameAction>
        <Item />
        <Standard />
      </Properties>
    </Template>
    <Template>
      <Name>BoardersItem</Name>
      <Properties>
        <BoardersBalancing />
        <GameAction>
          <ActionType>BoardingShip</ActionType>
          <TargetGUID>1518</TargetGUID>
          <TargetType>Handle</TargetType>
          <ActorType>Handle</ActorType>
        </GameAction>
        <Item>
          <ItemCategory>Ship</ItemCategory>
          <Passive>0</Passive>
          <ItemTarget>Object</ItemTarget>
          <StartQuestOnItemReceive>8050498</StartQuestOnItemReceive>
          <QuestStartDelay>30000</QuestStartDelay>
          <ItemType>Boarders</ItemType>
        </Item>
        <Standard />
      </Properties>
      <HiddenValues>
        <TargetGUID />
      </HiddenValues>
    </Template>
    <Template>
      <Name>BuildCostItem</Name>
      <Properties>
        <BuildCostUpgrade />
        <Item>
          <ItemCategory>Warehouse</ItemCategory>
          <ShowEffectIcon>0</ShowEffectIcon>
        </Item>
        <Standard />
        <Upgrade />
      </Properties>
    </Template>
    <Template>
      <Name>ConstructionItem</Name>
      <Properties>
        <GameAction>
          <ActionType>ConstructionPlan</ActionType>
          <TargetType>BuildGUID</TargetType>
          <ActorType>Handle</ActorType>
        </GameAction>
        <Item>
          <ItemCategory>Warehouse</ItemCategory>
          <Passive>0</Passive>
          <StartQuestOnItemReceive>8050717</StartQuestOnItemReceive>
          <QuestStartDelay>30000</QuestStartDelay>
          <RequireUserConfirmationOnRemove>1</RequireUserConfirmationOnRemove>
          <DestroyItemOnRemove>1</DestroyItemOnRemove>
          <ItemType>ConstructionPlan</ItemType>
        </Item>
        <Standard />
      </Properties>
    </Template>
    <Template>
      <Name>DoctorItem</Name>
      <Properties>
        <DoctorUpgrade />
        <Item>
          <ItemCategory>Warehouse</ItemCategory>
          <ItemTarget>Island</ItemTarget>
        </Item>
        <Standard />
        <Upgrade />
      </Properties>
    </Template>
    <Template>
      <Name>DocumentItem</Name>
      <Properties>
        <Document />
        <Item>
          <ItemCategory>Document</ItemCategory>
          <StartQuestOnItemReceive>8051019</StartQuestOnItemReceive>
          <QuestStartDelay>30000</QuestStartDelay>
          <ItemType>Document</ItemType>
          <ItemQuality>Document</ItemQuality>
        </Item>
        <Standard />
      </Properties>
    </Template>
    <Template>
      <Name>ExpeditionItem</Name>
      <Properties>
        <ExpeditionBalancing>
          <ExpeditionFailureDamageRange>
            <MinDamagePercent>30</MinDamagePercent>
            <MaxDamagePercent>100</MaxDamagePercent>
          </ExpeditionFailureDamageRange>
          <ExpeditionDuration>
            <MinDuration>420000</MinDuration>
            <MaxDuration>900000</MaxDuration>
          </ExpeditionDuration>
          <ExpeditionSuccessProbability>286720</ExpeditionSuccessProbability>
        </ExpeditionBalancing>
        <GameAction>
          <ActionType>Expedition</ActionType>
          <ActorType>Handle</ActorType>
        </GameAction>
        <Item>
          <ItemCategory>Ship</ItemCategory>
          <Passive>0</Passive>
          <ItemTarget>Object</ItemTarget>
          <RequiresUserConfirmationOnUse>1</RequiresUserConfirmationOnUse>
          <StartQuestOnItemReceive>8050718</StartQuestOnItemReceive>
          <QuestStartDelay>30000</QuestStartDelay>
          <ItemType>ExpeditionMap</ItemType>
        </Item>
        <Standard />
      </Properties>
      <HiddenValues>
        <TargetGUID />
      </HiddenValues>
    </Template>
    <Template>
      <Name>ExplosionItem</Name>
      <Properties>
        <ExplosionBalancing />
        <GameAction>
          <ActionType>ShipExplosion</ActionType>
          <ActorType>Handle</ActorType>
        </GameAction>
        <Item>
          <ItemCategory>Ship</ItemCategory>
          <Passive>0</Passive>
          <ItemTarget>Object</ItemTarget>
          <RequiresUserConfirmationOnUse>1</RequiresUserConfirmationOnUse>
          <StartQuestOnItemReceive>8050491</StartQuestOnItemReceive>
          <QuestStartDelay>30000</QuestStartDelay>
          <ItemType>PowderKeg</ItemType>
          <ShowCooldownInTooltip>0</ShowCooldownInTooltip>
        </Item>
        <Standard />
      </Properties>
      <HiddenValues>
        <TargetGUID />
      </HiddenValues>
    </Template>
    <Template>
      <Name>ForceTreatyItem</Name>
      <Properties>
        <ForceTreatyBalancing />
        <GameAction>
          <ActionType>ForceTreaty</ActionType>
          <ActorType>Handle</ActorType>
        </GameAction>
        <Item>
          <ItemCategory>Warehouse</ItemCategory>
          <Passive>0</Passive>
          <StartQuestOnItemReceive>8050470</StartQuestOnItemReceive>
          <QuestStartDelay>30000</QuestStartDelay>
          <ItemType>ForceTreaty</ItemType>
          <OnCooldownDuringEffectDuration>1</OnCooldownDuringEffectDuration>
          <ItemRemoveConditions>SinglePlayer</ItemRemoveConditions>
        </Item>
        <Standard />
      </Properties>
      <HiddenValues>
        <TargetGUID />
      </HiddenValues>
    </Template>
    <Template>
      <Name>ForeignFlagItem</Name>
      <Properties>
        <GameAction>
          <ActionType>ForeignFlag</ActionType>
          <ActorType>Handle</ActorType>
        </GameAction>
        <Item>
          <ItemCategory>Ship</ItemCategory>
          <UtilizationCount>1</UtilizationCount>
          <EffectDuration>60000</EffectDuration>
          <Cooldown>60000</Cooldown>
          <Passive>0</Passive>
          <ItemTarget>Object</ItemTarget>
          <RequiresUserConfirmationOnUse>1</RequiresUserConfirmationOnUse>
          <QuestStartDelay>30000</QuestStartDelay>
        </Item>
        <Standard />
      </Properties>
    </Template>
    <Template>
      <Name>IslandProductionBoostItem</Name>
      <Properties>
        <BuildCostUpgrade />
        <CostUpgrade />
        <FactoryUpgrade />
        <Item>
          <ItemCategory>Warehouse</ItemCategory>
          <ItemTarget>Island</ItemTarget>
        </Item>
        <ProductionUpgrade />
        <PublicBuildingUpgrade />
        <Standard />
        <Upgrade>
          <NeedsReinit>1</NeedsReinit>
        </Upgrade>
        <WarehouseUpgrade />
      </Properties>
      <HiddenValues>
        <Capacity />
        <ProductCost />
        <ProductionCapacity />
      </HiddenValues>
    </Template>
    <Template>
      <Name>LetterOfMarqueItem</Name>
      <Properties>
        <GameAction>
          <ActionType>LetterOfMarque</ActionType>
          <TargetType>None</TargetType>
          <ActorType>Handle</ActorType>
        </GameAction>
        <Item>
          <ItemCategory>Ship</ItemCategory>
          <UtilizationCount>1</UtilizationCount>
          <EffectDuration>60000</EffectDuration>
          <Passive>0</Passive>
          <ItemTarget>Object</ItemTarget>
          <RequiresUserConfirmationOnUse>1</RequiresUserConfirmationOnUse>
          <StartQuestOnItemReceive>8050477</StartQuestOnItemReceive>
          <QuestStartDelay>30000</QuestStartDelay>
          <ItemType>LetterOfMarque</ItemType>
          <OnCooldownDuringEffectDuration>1</OnCooldownDuringEffectDuration>
        </Item>
        <Standard />
      </Properties>
      <HiddenValues>
        <TargetGUID />
      </HiddenValues>
    </Template>
    <Template>
      <Name>MilitaryItem</Name>
      <Properties>
        <CostUpgrade />
        <HitpointUpgrade />
        <Item>
          <ItemCategory>Warehouse</ItemCategory>
          <UtilizationCount>1</UtilizationCount>
          <EffectDuration>60000</EffectDuration>
          <Passive>0</Passive>
          <ItemTarget>Island</ItemTarget>
          <RequiresUserConfirmationOnUse>1</RequiresUserConfirmationOnUse>
          <OnCooldownDuringEffectDuration>1</OnCooldownDuringEffectDuration>
          <ItemRemoveConditions>SinglePlayer</ItemRemoveConditions>
        </Item>
        <MilitaryUnitUpgrade />
        <Standard />
        <UnitUpgrade />
        <Upgrade>
          <NeedsReinit>1</NeedsReinit>
        </Upgrade>
      </Properties>
    </Template>
    <Template>
      <Name>MilitaryUpgrade</Name>
      <Properties>
        <CostUpgrade />
        <HitpointUpgrade />
        <Item>
          <ItemCategory>Warehouse</ItemCategory>
          <UtilizationCount>1</UtilizationCount>
          <EffectDuration>60000</EffectDuration>
          <Passive>0</Passive>
          <ItemTarget>Island</ItemTarget>
          <RequiresUserConfirmationOnUse>1</RequiresUserConfirmationOnUse>
          <OnCooldownDuringEffectDuration>1</OnCooldownDuringEffectDuration>
        </Item>
        <MilitaryUnitUpgrade />
        <Standard />
        <UnitUpgrade />
        <Upgrade>
          <NeedsReinit>1</NeedsReinit>
        </Upgrade>
      </Properties>
      <HiddenValues>
        <MoneyCost />
        <InactiveCost />
      </HiddenValues>
    </Template>
    <Template>
      <Name>PetItem</Name>
      <Properties>
        <GameAction>
          <ActionType>Pet</ActionType>
          <TargetType>None</TargetType>
          <ActorType>Handle</ActorType>
        </GameAction>
        <Item>
          <ItemCategory>Ship</ItemCategory>
          <Passive>0</Passive>
          <RequiresUserConfirmationOnUse>1</RequiresUserConfirmationOnUse>
          <ItemType>Pet</ItemType>
          <ItemQuality>C</ItemQuality>
        </Item>
        <Pet />
        <Standard />
      </Properties>
      <HiddenValues>
        <TargetGUID />
      </HiddenValues>
    </Template>
    <Template>
      <Name>PopulationItem</Name>
      <Properties>
        <GlobalUpgrade />
        <Item>
          <ItemCategory>Warehouse</ItemCategory>
        </Item>
        <Standard />
        <Upgrade />
      </Properties>
      <HiddenValues>
        <AmbassadorUpgradeRightBonus />
        <BeggarUpgradeRightBonus />
      </HiddenValues>
    </Template>
    <Template>
      <Name>PrestigeItem</Name>
      <Properties>
        <Item>
          <ItemCategory>Prestige</ItemCategory>
          <StartQuestOnItemReceive>8051138</StartQuestOnItemReceive>
          <QuestStartDelay>30000</QuestStartDelay>
          <ItemType>Prestige</ItemType>
          <ItemQuality>PrestigeItem</ItemQuality>
        </Item>
        <PrestigeItem />
        <Standard />
      </Properties>
    </Template>
    <Template>
      <Name>QuestItem</Name>
      <Properties>
        <Item>
          <ItemCategory>Quest</ItemCategory>
          <ItemType>QuestObject</ItemType>
        </Item>
        <Standard />
      </Properties>
    </Template>
    <Template>
      <Name>QuestUnitItem</Name>
      <Properties>
        <Item>
          <ItemCategory>Quest</ItemCategory>
          <IsQuestItem>1</IsQuestItem>
          <ItemType>QuestObject</ItemType>
          <SpawnFlotsamGUID>12555</SpawnFlotsamGUID>
        </Item>
        <Standard />
      </Properties>
    </Template>
    <Template>
      <Name>RepairShipItem</Name>
      <Properties>
        <Item>
          <ItemCategory>Ship</ItemCategory>
          <ItemTarget>Object</ItemTarget>
        </Item>
        <ShipRepairUpgrade />
        <Standard />
        <Upgrade />
      </Properties>
    </Template>
    <Template>
      <Name>SeaChartItem</Name>
      <Properties>
        <GameAction>
          <ActionType>SeaChart</ActionType>
          <TargetType>None</TargetType>
          <ActorType>Handle</ActorType>
        </GameAction>
        <Item>
          <ItemCategory>Ship</ItemCategory>
          <UtilizationCount>1</UtilizationCount>
          <Passive>0</Passive>
          <RequiresUserConfirmationOnUse>1</RequiresUserConfirmationOnUse>
          <ItemType>SeaChart</ItemType>
          <ItemQuality>B</ItemQuality>
          <ItemRemoveConditions>DiscoveredWorld</ItemRemoveConditions>
        </Item>
        <Standard />
      </Properties>
    </Template>
    <Template>
      <Name>SeedsItem</Name>
      <Properties>
        <GameAction>
          <ActionType>Fertility</ActionType>
          <TargetType>None</TargetType>
          <ActorType>Handle</ActorType>
        </GameAction>
        <Item>
          <ItemCategory>Warehouse</ItemCategory>
          <Passive>0</Passive>
          <RequiresUserConfirmationOnUse>1</RequiresUserConfirmationOnUse>
          <StartQuestOnItemReceive>8050456</StartQuestOnItemReceive>
          <QuestStartDelay>30000</QuestStartDelay>
          <RequireUserConfirmationOnRemove>1</RequireUserConfirmationOnRemove>
          <DestroyItemOnRemove>1</DestroyItemOnRemove>
          <ItemType>Seeds</ItemType>
        </Item>
        <Seed>
          <GeneratedFertility>Bees</GeneratedFertility>
          <GeneratedFertilityClime>North;South</GeneratedFertilityClime>
        </Seed>
        <Standard />
      </Properties>
      <HiddenValues>
        <TargetGUID />
      </HiddenValues>
    </Template>
    <Template>
      <Name>ShipItem</Name>
      <Properties>
        <CostUpgrade />
        <HitpointUpgrade />
        <Item>
          <ItemCategory>Ship</ItemCategory>
          <ItemTarget>Object</ItemTarget>
          <ItemType>ShipBoost</ItemType>
        </Item>
        <ShipCombatUpgrade />
        <ShipRepairUpgrade />
        <ShipUpgrade />
        <Standard />
        <TransportUpgrade />
        <UnitUpgrade />
        <Upgrade>
          <NeedsReinit>1</NeedsReinit>
        </Upgrade>
      </Properties>
      <HiddenValues>
        <MoneyCost />
      </HiddenValues>
    </Template>
    <Template>
      <Name>ShroudOfSmokeItem</Name>
      <Properties>
        <GameAction>
          <ActionType>ShroudOfSmoke</ActionType>
          <TargetType>None</TargetType>
          <ActorType>Handle</ActorType>
        </GameAction>
        <Item>
          <ItemCategory>Ship</ItemCategory>
          <Passive>0</Passive>
          <ItemTarget>Object</ItemTarget>
          <RequiresUserConfirmationOnUse>1</RequiresUserConfirmationOnUse>
          <StartQuestOnItemReceive>8050505</StartQuestOnItemReceive>
          <QuestStartDelay>30000</QuestStartDelay>
          <ItemType>ShroudOfSmoke</ItemType>
        </Item>
        <ShroudOfSmokeBalancing>
          <ShroudUIColor>
            <R>240</R>
            <A>100</A>
          </ShroudUIColor>
        </ShroudOfSmokeBalancing>
        <Standard />
      </Properties>
      <HiddenValues>
        <TargetGUID />
      </HiddenValues>
    </Template>
    <Template>
      <Name>TollItem</Name>
      <Properties>
        <Item>
          <ItemCategory>Warehouse</ItemCategory>
          <UtilizationCount>1</UtilizationCount>
          <Passive>0</Passive>
          <ItemTarget>Island</ItemTarget>
          <RequiresUserConfirmationOnUse>1</RequiresUserConfirmationOnUse>
          <StartQuestOnItemReceive>8050519</StartQuestOnItemReceive>
          <QuestStartDelay>30000</QuestStartDelay>
          <ItemType>Toll</ItemType>
        </Item>
        <Standard />
        <TollBalancing />
        <Upgrade>
          <TargetCategories>TradeBuildings</TargetCategories>
        </Upgrade>
      </Properties>
    </Template>
    <Template>
      <Name>TrashItem</Name>
      <Properties>
        <Item>
          <ItemCategory>Quest</ItemCategory>
          <ItemType>QuestObject</ItemType>
        </Item>
        <Standard />
      </Properties>
    </Template>
    <Template>
      <Name>WarehouseItem</Name>
      <Properties>
        <BuildCostUpgrade />
        <CostUpgrade />
        <Item>
          <ItemCategory>Warehouse</ItemCategory>
          <ItemTarget>Island</ItemTarget>
        </Item>
        <Standard />
        <Upgrade>
          <NeedsReinit>1</NeedsReinit>
        </Upgrade>
        <WarehouseUpgrade />
      </Properties>
      <HiddenValues>
        <InactiveCost />
        <ActiveCost />
      </HiddenValues>
    </Template>
    <Template>
      <Name>WhiteFlagItem</Name>
      <Properties>
        <GameAction>
          <ActionType>WhiteFlag</ActionType>
          <TargetType>None</TargetType>
          <ActorType>Handle</ActorType>
        </GameAction>
        <Item>
          <ItemCategory>Ship</ItemCategory>
          <UtilizationCount>1</UtilizationCount>
          <EffectDuration>60000</EffectDuration>
          <Passive>0</Passive>
          <ItemTarget>Object</ItemTarget>
          <RequiresUserConfirmationOnUse>1</RequiresUserConfirmationOnUse>
          <StartQuestOnItemReceive>8050484</StartQuestOnItemReceive>
          <QuestStartDelay>30000</QuestStartDelay>
          <ItemType>WhiteFlag</ItemType>
          <OnCooldownDuringEffectDuration>1</OnCooldownDuringEffectDuration>
        </Item>
        <Standard />
      </Properties>
      <HiddenValues>
        <TargetGUID />
      </HiddenValues>
    </Template>
    <Template>
      <Name>WirtschaftExperte</Name>
      <Properties>
        <CostUpgrade />
        <FactoryUpgrade />
        <Item>
          <ItemCategory>Warehouse</ItemCategory>
          <ItemTarget>Island</ItemTarget>
          <RequireUserConfirmationOnRemove>1</RequireUserConfirmationOnRemove>
          <DestroyItemOnRemove>1</DestroyItemOnRemove>
        </Item>
        <ProductionUpgrade />
        <PublicBuildingUpgrade />
        <Standard />
        <Upgrade>
          <NeedsReinit>1</NeedsReinit>
        </Upgrade>
        <WarehouseUpgrade />
      </Properties>
      <HiddenValues>
        <HonorCost />
        <MoneyCost />
        <RawCapacity1 />
        <RawCapacity2 />
        <RawNeeded1 />
        <RawNeeded2 />
        <ProductionCapacity />
        <ProductionTime />
        <InfluenceRadius />
        <BuildingDemandEfficiency />
        <Capacity />
      </HiddenValues>
    </Template>
  </Group>
  <Group>
    <Name>Talents</Name>
    <Template>
      <Name>ActiveTalent</Name>
      <IsExpertTemplate>1</IsExpertTemplate>
      <Properties>
        <ActiveTalent />
        <GameAction>
          <ActorType>Player</ActorType>
        </GameAction>
        <Preconditions />
        <Standard />
        <Talent />
      </Properties>
    </Template>
    <Template>
      <Name>DiplomacyTalent</Name>
      <IsExpertTemplate>1</IsExpertTemplate>
      <Properties>
        <ActiveTalent />
        <DiplomacyBalancing>
          <ProbabilityOfSuccess>60</ProbabilityOfSuccess>
        </DiplomacyBalancing>
        <GameAction>
          <ActorType>Player</ActorType>
        </GameAction>
        <Preconditions />
        <Standard />
        <Talent />
      </Properties>
    </Template>
    <Template>
      <Name>PassiveDiplomacyTalent</Name>
      <IsExpertTemplate>1</IsExpertTemplate>
      <Properties>
        <DiplomacyBalancing>
          <ProbabilityOfSuccess>60</ProbabilityOfSuccess>
        </DiplomacyBalancing>
        <GameAction>
          <TargetType>None</TargetType>
          <ActorType>Player</ActorType>
        </GameAction>
        <Preconditions />
        <Standard />
        <Talent />
      </Properties>
    </Template>
    <Template>
      <Name>PassiveTalent</Name>
      <IsExpertTemplate>1</IsExpertTemplate>
      <Properties>
        <GameAction>
          <ActorType>Player</ActorType>
        </GameAction>
        <Preconditions />
        <Standard />
        <Talent />
      </Properties>
    </Template>
    <Template>
      <Name>UpgradeTalent</Name>
      <IsExpertTemplate>1</IsExpertTemplate>
      <Properties>
        <GameAction>
          <TargetType>None</TargetType>
          <ActorType>Player</ActorType>
        </GameAction>
        <GlobalUpgrade />
        <Preconditions />
        <Standard />
        <Talent />
      </Properties>
    </Template>
  </Group>
  <Group>
    <Name>GlobalUpgrades</Name>
    <Template>
      <Name>GlobalBuildingUpgrade</Name>
      <Properties>
        <HitpointUpgrade />
        <Standard />
        <Upgrade />
      </Properties>
    </Template>
    <Template>
      <Name>GlobalCorsairUpgrade</Name>
      <Properties>
        <ShipTradeUpgrade />
        <Standard />
      </Properties>
    </Template>
    <Template>
      <Name>GlobalDiplomacyUpgrade</Name>
      <Properties>
        <DiplomacyUpgrade />
        <Standard />
      </Properties>
    </Template>
    <Template>
      <Name>GlobalGlobalUpgrade</Name>
      <Properties>
        <GlobalUpgrade />
        <Standard />
      </Properties>
      <HiddenValues>
        <DemandAmount />
        <TaxUpgradePercent />
        <ResidenceUpgradeAmountMaxPercent />
      </HiddenValues>
    </Template>
    <Template>
      <Name>GlobalHarborTower</Name>
      <Properties>
        <HitpointUpgrade />
        <Standard />
        <Upgrade />
        <MilitaryUnitUpgrade />
      </Properties>
    </Template>
    <Template>
      <Name>GlobalMilitaryUpgrade</Name>
      <Properties>
        <HitpointUpgrade />
        <MilitaryUnitUpgrade />
        <Standard />
        <UnitUpgrade />
        <Upgrade>
          <NeedsReinit>1</NeedsReinit>
        </Upgrade>
      </Properties>
      <HiddenValues>
        <AttackDelayCloseCombat />
        <AttackDelayRangeCombat />
        <DamageEfficiency />
        <WalkingSpeed />
      </HiddenValues>
    </Template>
    <Template>
      <Name>GlobalProductionBoostUpgrade</Name>
      <Properties>
        <ProductionUpgrade />
        <Standard />
        <Upgrade>
          <NeedsReinit>1</NeedsReinit>
        </Upgrade>
      </Properties>
      <HiddenValues>
        <WorkerCount />
      </HiddenValues>
    </Template>
    <Template>
      <Name>GlobalTradingShipUpgrade</Name>
      <Properties>
        <HitpointUpgrade />
        <ShipRepairUpgrade />
        <ShipUpgrade />
        <Standard />
        <TransportUpgrade />
        <UnitUpgrade />
        <Upgrade>
          <NeedsReinit>1</NeedsReinit>
        </Upgrade>
      </Properties>
      <HiddenValues>
        <HealingPointsPerMinute />
        <RepairRadius />
        <SelfHealingPointsPerMinute />
      </HiddenValues>
    </Template>
    <Template>
      <Name>GlobalTributeUpgrade</Name>
      <Properties>
        <Standard />
        <TributeUpgrade />
      </Properties>
    </Template>
    <Template>
      <Name>GlobalUnitLimitUpgrade</Name>
      <Properties>
        <Standard />
        <UnitLimitUpgrade />
      </Properties>
    </Template>
    <Template>
      <Name>GlobalWarShipUpgrade</Name>
      <Properties>
        <HitpointUpgrade />
        <ShipCombatUpgrade />
        <ShipRepairUpgrade />
        <ShipUpgrade />
        <Standard />
        <UnitUpgrade />
        <Upgrade>
          <NeedsReinit>1</NeedsReinit>
        </Upgrade>
      </Properties>
    </Template>
  </Group>
  <Group>
    <Name>Addon</Name>
    <Group>
      <Name>Items</Name>
      <Template>
        <Name>EndlessResourceItem</Name>
        <Properties>
          <Item>
            <ItemCategory>Warehouse</ItemCategory>
            <ItemTarget>Island</ItemTarget>
            <StartQuestOnItemReceive>40670900</StartQuestOnItemReceive>
            <QuestStartDelay>30000</QuestStartDelay>
            <ItemType>EndlessResource</ItemType>
          </Item>
          <EndlessResource />
          <CostUpgrade />
          <Upgrade>
            <TargetGUIDs>
              <Item />
            </TargetGUIDs>
            <NeedsReinit>1</NeedsReinit>
          </Upgrade>
          <Standard />
        </Properties>
      </Template>
      <Template>
        <Name>SpyBaseDetectionItem</Name>
        <Properties>
          <Standard />
          <Item>
            <ItemCategory>Ship</ItemCategory>
            <UtilizationCount>1</UtilizationCount>
            <EffectDuration>240000</EffectDuration>
            <Passive>0</Passive>
            <RequiresUserConfirmationOnUse>1</RequiresUserConfirmationOnUse>
            <ItemType>DiscoverSpyBases</ItemType>
            <ItemQuality>B</ItemQuality>
            <OnCooldownDuringEffectDuration>1</OnCooldownDuringEffectDuration>
            <ItemRemoveConditions>NoEspionage</ItemRemoveConditions>
          </Item>
          <GameAction>
            <ActionType>DiscoverSpyBases</ActionType>
            <TargetType>None</TargetType>
            <ActorType>Handle</ActorType>
            <AbortItemUseOnFailedAction>1</AbortItemUseOnFailedAction>
          </GameAction>
          <SpyBaseDetectionBalancing />
        </Properties>
      </Template>
      <Template>
        <Name>SpyBaseItem</Name>
        <Properties>
          <Standard />
          <Upgrade>
            <TargetGUIDs>
              <Item>
                <UpgradeGUID>40001000</UpgradeGUID>
              </Item>
            </TargetGUIDs>
            <NeedsReinit>1</NeedsReinit>
          </Upgrade>
          <Item>
            <ItemCategory>Warehouse</ItemCategory>
            <ItemTarget>Island</ItemTarget>
            <ItemQuality>B</ItemQuality>
            <ItemRemoveConditions>NoEspionage</ItemRemoveConditions>
          </Item>
          <PublicBuildingUpgrade />
          <CostUpgrade />
          <ProductionUpgrade>
            <WorkerCountType>AntiSpyUnit</WorkerCountType>
          </ProductionUpgrade>
        </Properties>
      </Template>
      <Template>
        <Name>VenetianItem</Name>
        <Properties>
          <Item>
            <ItemCategory>Warehouse</ItemCategory>
            <ItemTarget>Island</ItemTarget>
          </Item>
          <Standard />
          <VenetianUpgrade />
        </Properties>
      </Template>
    </Group>
    <Group>
      <Name>Espionage</Name>
    </Group>
    <Template>
      <Name>CustomResourceItem</Name>
      <Properties>
        <Item>
          <ItemCategory>Warehouse</ItemCategory>
          <Passive>0</Passive>
          <ItemTarget>Island</ItemTarget>
          <StartQuestOnItemReceive>40670900</StartQuestOnItemReceive>
          <QuestStartDelay>30000</QuestStartDelay>
          <DestroyItemOnRemove>1</DestroyItemOnRemove>
          <ItemType>CustomResource</ItemType>
          <ItemRemoveConditions>NoVolcano</ItemRemoveConditions>
        </Item>
        <Upgrade>
          <TargetGUIDs>
            <Item>
              <UpgradeGUID>600</UpgradeGUID>
            </Item>
            <Item />
            <Item />
          </TargetGUIDs>
          <ShowTargetInTooltip>0</ShowTargetInTooltip>
          <NeedsReinit>1</NeedsReinit>
        </Upgrade>
        <Standard />
        <CustomResource>
          <CustomResources>Quartz;Copper;Gold</CustomResources>
        </CustomResource>
      </Properties>
    </Template>
    <Template>
      <Name>EnforceProtestAction</Name>
      <Properties>
        <Item>
          <ItemQuality>Document</ItemQuality>
          <ItemRemoveConditions>NoEspionage</ItemRemoveConditions>
        </Item>
        <Upgrade />
        <Standard />
        <EnforceProtest />
        <GameAction>
          <ActionType>SabotageEnforceProtest</ActionType>
          <TargetType>None</TargetType>
          <ActorType>Handle</ActorType>
        </GameAction>
      </Properties>
    </Template>
    <Template>
      <Name>GlobalVenetianUpgrade</Name>
      <Properties>
        <VenetianUpgrade />
        <Standard />
        <BuildCostUpgrade />
        <Upgrade />
        <CostUpgrade />
      </Properties>
    </Template>
    <Template>
      <Name>ProphetAction</Name>
      <Properties>
        <Standard />
        <Upgrade />
        <Item>
          <ItemQuality>Document</ItemQuality>
          <ItemRemoveConditions>NoEspionage</ItemRemoveConditions>
        </Item>
        <GameAction>
          <ActionType>SabotageProphet</ActionType>
          <TargetType>None</TargetType>
          <ActorType>Player</ActorType>
        </GameAction>
        <SabotageProphet />
      </Properties>
    </Template>
  </Group>
</Templates>